{
  "learningHubData": {
    "sections": [
        {
          "id": "c-programming",
          "title": "C Programming Certifications",
          "description": "Master C programming with these certification courses, from basics to advanced concepts.",
          "resources": [
            {
              "name": "C Programming for Beginners Certification (Udemy)",
              "url": "https://www.udemy.com/course/c-programming-for-beginners-/",
              "type": "Online Course",
              "description": "Comprehensive C programming course with certification. Covers syntax, pointers, memory management, and more.",
              "tags": ["C Programming", "Beginner", "Paid", "Certificate"]
            },
            {
              "name": "Advanced C Programming Course (Coursera)",
              "url": "https://www.coursera.org/specializations/c-programming",
              "type": "Specialization",
              "description": "Master advanced C programming concepts with hands-on projects and earn a verified certificate.",
              "tags": ["C Programming", "Advanced", "Free to Audit", "Certificate"]
            },
            {
              "name": "C Programming with Linux Professional Certificate (edX)",
              "url": "https://www.edx.org/professional-certificate/dartmouth-imtx-c-programming-with-linux",
              "type": "Professional Certificate",
              "description": "Learn C programming and Linux together, earn a verified professional certificate from Dartmouth.",
              "tags": ["C Programming", "Linux", "Free to Audit", "Certificate"]
            },
            {
              "name": "Introduction to C Programming (FreeCodeCamp)",
              "url": "https://www.freecodecamp.org/learn/scientific-computing-with-python/",
              "type": "Online Course",
              "description": "Free certification course covering C programming fundamentals with hands-on exercises.",
              "tags": ["C Programming", "Beginner", "Free", "Certificate"]
            },
            {
              "name": "C Programming Master Course (CodeCademy)",
              "url": "https://www.codecademy.com/learn/learn-c",
              "type": "Interactive Course",
              "description": "Interactive C programming course with hands-on coding exercises and certification.",
              "tags": ["C Programming", "Interactive", "Paid", "Certificate"]
            }
             ,{
                "name": "Scaler Topics: C Programming (Free)",
                "url": "https://www.scaler.com/topics/c/",
                "type": "Online Course",
                "description": "A comprehensive, free C programming course by Scaler Topics. Covers basics to advanced topics, includes quizzes and coding practice. No certificate, but great for learning and interview prep.",
                "tags": ["C Programming", "Beginner", "Free", "Practice"]
              },
              {
                "name": "Data Structures with C (NPTEL, IIT Kharagpur)",
                "url": "https://nptel.ac.in/courses/106105085",
                "type": "Online Course",
                "description": "Advanced course covering data structures implementation in C. Learn from IIT Kharagpur faculty with programming assignments and examples.",
                "tags": ["C Programming", "Data Structures", "Advanced", "Free", "Certificate", "Recommended"]
              },
              {
                "name": "Problem Solving with C (NPTEL, IIT Kharagpur)",
                "url": "https://nptel.ac.in/courses/106105171",
                "type": "Online Course",
                "description": "Learn problem-solving techniques using C programming. Includes algorithmic thinking and practical coding exercises from IIT Kharagpur.",
                "tags": ["C Programming", "Problem Solving", "Algorithms", "Free", "Certificate", "Recommended"]
              },
              {
                "name": "Data Structures and Algorithms with C (NPTEL)",
                "url": "https://nptel.ac.in/courses/106106127",
                "type": "Online Course",
                "description": "Comprehensive course covering DSA implementation in C. Includes theoretical concepts and practical implementations with detailed examples.",
                "tags": ["C Programming", "Data Structures", "Algorithms", "Advanced", "Free", "Certificate", "Recommended"]
              },
              {
                "name": "C Language Tutorial in Hindi (CodeWithHarry)",
                "url": "https://www.youtube.com/watch?v=7Dh73z3icd8&list=PLu0W_9lII9aiXlHcLx-mDH1Qul38wD3aR",
                "type": "YouTube Playlist",
                "description": "Complete C programming tutorial series in Hindi by CodeWithHarry. Perfect for beginners with practical examples and coding exercises.",
                "tags": ["C Programming", "Beginner", "Video", "Hindi", "Free", "Recommended"]
              }
          ]
        },
        {
          "id": "java-programming",
          "title": "Java Programming Certifications",
          "description": "Comprehensive Java courses and certification paths — free and paid — for beginners through advanced learners.",
          "resources": [
            {
              "name": "Java Programming (MOOC.fi)",
              "url": "https://java-programming.mooc.fi/",
              "type": "Online Course",
              "description": "University of Helsinki's free, self-paced Java Programming I & II course. Includes extensive exercises and certificates available via the MOOC.fi profile completions page.",
              "tags": ["Java", "Beginner", "Free", "Certificate", "Recommended"]
            },
            {
              "name": "CodeWithHarry - Java Tutorials (Playlist)",
              "url": "https://www.youtube.com/playlist?list=PLu0W_9lII9agS67Uits0UnJyrYiXhDS6q",
              "type": "YouTube Playlist",
              "description": "Beginner-friendly Java tutorials by CodeWithHarry. Practical examples and Hindi/English explanations — great for hands-on learning.",
              "tags": ["Java", "Beginner", "Video", "Free", "Recommended"]
            },
            {
              "name": "Abdul Bari - Java SE Programming (Udemy)",
              "url": "https://www.udemy.com/course/java-se-programming/?couponCode=PMNVD2025",
              "type": "Online Course",
              "description": "Abdul Bari's comprehensive Java SE Programming course on Udemy. In-depth coverage of core Java concepts with excellent teaching methodology. Highly recommended for conceptual clarity.",
              "tags": ["Java", "Paid", "Video", "Recommended"]
            },
            {
              "name": "Java Programming and Software Engineering Fundamentals (Coursera)",
              "url": "https://www.coursera.org/specializations/java-programming",
              "type": "Specialization",
              "description": "A multi-course specialization covering Java programming, data structures, and software engineering fundamentals. Free to audit, paid for verified certificate.",
              "tags": ["Java", "Specialization", "Free to Audit", "Certificate"]
            },
            {
              "name": "Java Programming: Complete Beginner to Advanced (Udemy)",
              "url": "https://www.udemy.com/course/java-programming-complete-beginner-to-advanced/",
              "type": "Online Course",
              "description": "Popular Udemy course covering core Java from basics to advanced topics with exercises and a completion certificate.",
              "tags": ["Java", "Beginner", "Paid", "Certificate"]
            },
            {
              "name": "Java In-Depth: Become a Complete Java Engineer (Udemy)",
              "url": "https://www.udemy.com/course/java-in-depth-become-a-complete-java-engineer/",
              "type": "Online Course",
              "description": "Comprehensive paid course on Udemy that covers modern Java development practices and interview preparation.",
              "tags": ["Java", "Advanced", "Paid", "Certificate"]
            }
          ]
        },
      {
        "id": "core-programming",
        "title": "Core Programming",
        "description": "Foundational programming courses from the OSSU curriculum.",
        "resources": [
          {
            "name": "Systematic Program Design (UBC, edX)",
            "url": "https://www.edx.org/course/systematic-program-design-part-1",
            "type": "Online Course",
            "description": "Learn systematic program design and functional programming principles.",
            "tags": ["Programming", "Functional", "Free"]
          },
          {
            "name": "Programming Languages (UW, Coursera)",
            "url": "https://www.coursera.org/learn/programming-languages",
            "type": "Online Course",
            "description": "Covers the basic concepts of programming languages and interpreters.",
            "tags": ["Programming", "Languages", "Free to Audit"]
          },
          {
            "name": "Object-Oriented Design (UCSD, Coursera)",
            "url": "https://www.coursera.org/learn/object-oriented-design",
            "type": "Online Course",
            "description": "Learn object-oriented design and software architecture.",
            "tags": ["Programming", "OOP", "Free to Audit"]
          }
        ]
      },
      {
        "id": "core-systems",
        "title": "Core Systems",
        "description": "Systems and computer architecture resources from OSSU.",
        "resources": [
          {
            "name": "Nand to Tetris: Build a Modern Computer (Coursera)",
            "url": "https://www.coursera.org/learn/build-a-computer",
            "type": "Online Course",
            "description": "Build a computer from first principles, from logic gates to operating systems.",
            "tags": ["Systems", "Hardware", "Free to Audit"]
          },
          {
            "name": "Operating Systems: Three Easy Pieces (Book)",
            "url": "https://pages.cs.wisc.edu/~remzi/OSTEP/",
            "type": "Book",
            "description": "A free, comprehensive book on operating systems concepts.",
            "tags": ["Operating Systems", "Book", "Free"]
          }
        ]
      },
      {
        "id": "core-theory",
        "title": "Core Theory",
        "description": "Algorithm and theory resources from OSSU.",
        "resources": [
          {
            "name": "Divide and Conquer, Sorting and Searching, and Randomized Algorithms (Stanford, Coursera)",
            "url": "https://www.coursera.org/learn/algorithms-divide-conquer",
            "type": "Online Course",
            "description": "Learn core algorithmic techniques for problems that arise in computing applications.",
            "tags": ["Algorithms", "Theory", "Free to Audit"]
          },
          {
            "name": "Greedy Algorithms, Minimum Spanning Trees, and Dynamic Programming (Stanford, Coursera)",
            "url": "https://www.coursera.org/learn/algorithms-greedy",
            "type": "Online Course",
            "description": "Explore greedy algorithms, minimum spanning trees, and dynamic programming.",
            "tags": ["Algorithms", "Theory", "Free to Audit"]
          }
        ]
      },
      {
        "id": "core-security",
        "title": "Core Security",
        "description": "Cybersecurity fundamentals from OSSU.",
        "resources": [
          {
            "name": "Cybersecurity Fundamentals (RIT, edX)",
            "url": "https://www.edx.org/course/cybersecurity-fundamentals",
            "type": "Online Course",
            "description": "Introduction to cybersecurity principles and practices.",
            "tags": ["Security", "Cybersecurity", "Free to Audit"]
          }
        ]
      },
      {
        "id": "core-applications",
        "title": "Core Applications",
        "description": "Databases, machine learning, and application-focused resources from OSSU.",
        "resources": [
          {
            "name": "Databases: Modeling and Theory (Stanford, edX)",
            "url": "https://www.edx.org/course/databases-5-sql",
            "type": "Online Course",
            "description": "Covers relational databases, SQL, and data modeling.",
            "tags": ["Databases", "SQL", "Free"]
          },
          {
            "name": "Machine Learning (Stanford, Coursera)",
            "url": "https://www.coursera.org/learn/machine-learning",
            "type": "Online Course",
            "description": "Andrew Ng's famous machine learning course.",
            "tags": ["Machine Learning", "AI", "Free to Audit"]
          }
        ]
      },
      {
        "id": "core-math",
        "title": "Core Math",
        "description": "Essential mathematics for computer science, including calculus and discrete math.",
        "resources": [
          {
            "name": "Calculus 1A: Differentiation (MIT)",
            "url": "https://www.edx.org/course/calculus-1a-differentiation",
            "type": "Online Course",
            "description": "Learn the basics of differentiation in calculus from MIT on edX.",
            "tags": ["Calculus", "Math", "Free"]
          },
          {
            "name": "Calculus 1B: Integration (MIT)",
            "url": "https://www.edx.org/course/calculus-1b-integration",
            "type": "Online Course",
            "description": "Covers the fundamentals of integration in calculus, from MIT on edX.",
            "tags": ["Calculus", "Math", "Free"]
          },
          {
            "name": "Calculus 1C: Coordinate Systems & Infinite Series (MIT)",
            "url": "https://www.edx.org/course/calculus-1c-coordinate-systems-infinite-series",
            "type": "Online Course",
            "description": "Explore coordinate systems and infinite series in calculus, from MIT on edX.",
            "tags": ["Calculus", "Math", "Free"]
          },
          {
            "name": "Mathematics for Computer Science (MIT OCW)",
            "url": "https://ocw.mit.edu/courses/electrical-engineering-and-computer-science/6-042j-mathematics-for-computer-science-fall-2010/",
            "type": "Online Course",
            "description": "Discrete mathematics and proofs for computer science, from MIT OpenCourseWare.",
            "tags": ["Discrete Math", "Math", "Free"]
          }
        ]
      },
      {
        "id": "cs-fundamentals",
        "title": "Computer Science Fundamentals",
        "description": "Start your journey here with the core concepts of computation, data structures, and algorithms that power all software.",
        "resources": [
          {
            "name": "Harvard's CS50x",
            "url": "https://www.edx.org/course/introduction-computer-science-harvardx-cs50x",
            "type": "Online Course",
            "description": "The definitive introduction to computer science. Engaging, comprehensive, and free.",
            "tags": ["Beginner", "Video", "Free"]
          },
          {
            "name": "Abdul Bari's Algorithms Playlist",
            "url": "https://www.youtube.com/playlist?list=PLDN4rrl48XKpZkf03iYFl-O29szjTrs_O",
            "type": "YouTube Playlist",
            "description": "Legendary YouTube playlist that masterfully explains complex algorithms.",
            "tags": ["Algorithms", "Video", "Free"]
          },
          {
            "name": "GeeksforGeeks",
            "url": "https://www.geeksforgeeks.org/",
            "type": "Website",
            "description": "A vast library of articles and code examples for data structures and algorithms.",
            "tags": ["Articles", "Code", "Free"]
          },
          {
            "name": "freeCodeCamp - Data Structures Course",
            "url": "https://www.youtube.com/watch?v=RBSGKlAcrPw",
            "type": "YouTube Course",
            "description": "A full 8-hour YouTube course covering everything you need for data structures.",
            "tags": ["Data Structures", "Video", "Free"]
          }
        ]
      },
      {
        "id": "web-development-frontend",
        "title": "Web Development (Frontend)",
        "description": "Learn to build beautiful and interactive user interfaces for websites and web applications.",
        "resources": [
          {
            "name": "The Odin Project",
            "url": "https://www.theodinproject.com/",
            "type": "Interactive Platform",
            "description": "A complete, project-based curriculum for becoming a full-stack developer.",
            "tags": ["Full-Stack", "Project-based", "Free"]
          },
          {
            "name": "MDN Web Docs",
            "url": "https://developer.mozilla.org/",
            "type": "Documentation",
            "description": "The ultimate reference for all web technologies (HTML, CSS, JS).",
            "tags": ["Reference", "Articles", "Free"]
          },
          {
            "name": "Kevin Powell's YouTube Channel",
            "url": "https://www.youtube.com/channel/UCJZv4d5rbIKd4QHMPkcABCw",
            "type": "YouTube Channel",
            "description": "A master of CSS. His tutorials make complex CSS simple and fun.",
            "tags": ["CSS", "Video", "Free"]
          },
          {
            "name": "Fireship.io",
            "url": "https://www.youtube.com/c/Fireship",
            "type": "YouTube Channel",
            "description": "Fast-paced, modern tutorials on JavaScript and popular frameworks.",
            "tags": ["JavaScript", "Frameworks", "Video", "Free"]
          }
        ]
      },
      {
        "id": "web-development-backend",
        "title": "Web Development (Backend)",
        "description": "Power your applications by learning how to work with servers, databases, and APIs.",
        "resources": [
          {
            "name": "CodeWithHarry",
            "url": "https://www.youtube.com/c/CodeWithHarry",
            "type": "YouTube Channel",
            "description": "Excellent resource (Hindi/English) for Node.js, Python with Django, and databases.",
            "tags": ["Node.js", "Python", "Hindi", "Free"]
          },
          {
            "name": "Traversy Media",
            "url": "https://www.youtube.com/c/TraversyMedia",
            "type": "YouTube Channel",
            "description": "Countless project-based tutorials on Node.js, Express, and databases.",
            "tags": ["Node.js", "Projects", "Video", "Free"]
          },
          {
            "name": "PostgreSQL Exercises",
            "url": "https://pgexercises.com/",
            "type": "Interactive Platform",
            "description": "Practice your SQL skills with this interactive website.",
            "tags": ["SQL", "Database", "Free"]
          }
        ]
      },
      {
        "id": "ai-machine-learning",
        "title": "AI & Machine Learning",
        "description": "Dive into the world of artificial intelligence, learning how to build models that can learn from data.",
        "resources": [
          {
            "name": "Andrew Ng's ML Specialization",
            "url": "https://www.coursera.org/specializations/machine-learning-introduction",
            "type": "Online Course",
            "description": "The most famous and highly-recommended introductory course on the topic.",
            "tags": ["Beginner", "Theory", "Free to Audit"]
          },
          {
            "name": "Krish Naik's YouTube Channel",
            "url": "https://www.youtube.com/@krishnaik06",
            "type": "YouTube Channel",
            "description": "Massive collection of playlists covering everything in ML, deep learning, and data science.",
            "tags": ["AI", "Python", "Video", "Free"]
          },
          {
            "name": "Kaggle",
            "url": "https://www.kaggle.com/",
            "type": "Platform",
            "description": "The best platform for practicing your ML skills with real-world datasets and competitions.",
            "tags": ["Practice", "Datasets", "Free"]
          }
        ]
      },
      {
        "id": "essential-tools",
        "title": "Essential Tools & Practices",
        "description": "Master the essential tools and workflows that every professional developer uses daily.",
        "resources": [
          {
            "name": "Git - The Simple Guide",
            "url": "https://rogerdudler.github.io/git-guide/",
            "type": "Website",
            "description": "A straightforward, no-nonsense guide to getting started with Git.",
            "tags": ["Git", "Version Control", "Free"]
          },
          {
            "name": "GitHub Skills",
            "url": "https://skills.github.com/",
            "type": "Interactive Platform",
            "description": "Fun, interactive courses to learn how to use GitHub effectively.",
            "tags": ["Git", "GitHub", "Free"]
          },
          {
            "name": "Learn Command Line",
            "url": "https://www.learnenough.com/command-line-tutorial",
            "type": "Website",
            "description": "A free and simple introduction to the command line interface.",
            "tags": ["Tools", "Command Line", "Free"]
          }
        ]
      },
      {
        "id": "career-prep",
        "title": "Career Preparation",
        "description": "Prepare for the job market with interview practice, resume tips, and portfolio guidance.",
        "resources": [
          {
            "name": "LeetCode",
            "url": "https://leetcode.com/",
            "type": "Platform",
            "description": "The premier platform for practicing coding interview questions.",
            "tags": ["Interviews", "Algorithms", "Freemium"]
          },
          {
            "name": "Gaurav Sen's System Design Playlist",
            "url": "https://www.youtube.com/playlist?list=PLMCXHnjXnTnvo5hDYws0p_TCDZkgc8G7D",
            "type": "YouTube Playlist",
            "description": "A fantastic resource for understanding how to design large-scale systems.",
            "tags": ["System Design", "Interviews", "Free"]
          },
          {
            "name": "FreeCodeCamp - Responsive Web Design",
            "url": "https://www.freecodecamp.org/learn/responsive-web-design/",
            "type": "Interactive Course",
            "description": "Hands-on interactive web design curriculum for HTML & CSS",
            "tags":  ["HTML", "CSS", "Beginner", "Free"]
          }
        ]
      }
    ]
  }
}